myPackage/__init__.py
myPackage/somePython.py
python_sample_package-0.4.0.dist-info/DESCRIPTION.rst
python_sample_package-0.4.0.dist-info/METADATA
python_sample_package-0.4.0.dist-info/RECORD
python_sample_package-0.4.0.dist-info/WHEEL
python_sample_package-0.4.0.dist-info/metadata.json
python_sample_package-0.4.0.dist-info/top_level.txt
