Metadata-Version: 2.0
Name: python-sample-package
Version: 0.4.0
Summary: An example python package
Home-page: https://github.com/iiddoo/python-sample-package.git
Author: Ido Lev
Author-email: iiddoolleevv@gmail.com
License: MIT
Platform: UNKNOWN
Classifier: Programming Language :: Python :: 3
Classifier: License :: OSI Approved :: MIT License
Classifier: Operating System :: OS Independent
Requires-Dist: numpy
